<?xml version="1.0" encoding="UTF-8" standalone="yes"?><imgdir name="3003233.img"><imgdir name="info"></imgdir><imgdir name="stand"><canvas name="0" width="1" height="1"><vector name="origin" x="21" y="68"/><int name="z" value="0"/><string name="_hash" value="9999714edcf16a14ffa8ab149110bf66addf9a433652f5fad3b6eaf68dffbdbb"/><string name="_outlink" value="Npc/3003225.img/stand/0"/></canvas></imgdir><imgdir name="condition1"><uol name="stand" value="../stand"/><int name="34325" value="2"/></imgdir><imgdir name="condition2"><imgdir name="stand"><canvas name="0" width="58" height="68"><vector name="origin" x="21" y="68"/><int name="z" value="0"/><int name="delay" value="150"/><string name="_hash" value="db530adec3779b1170eaa120f5021c30c3a7195011759a694c5bf10928a5dcc2"/></canvas><canvas name="1" width="58" height="68"><vector name="origin" x="21" y="68"/><int name="z" value="0"/><int name="delay" value="150"/><string name="_hash" value="5e2a00aadb24c82d28d114364229212ea64880b6145657d852860cc33b7e922f"/></canvas></imgdir><int name="34315" value="2"/></imgdir></imgdir>